fastapi_file_router-0.1.17.dist-info/METADATA
fastapi_file_router-0.1.17.dist-info/WHEEL
fastapi_file_router-0.1.17.dist-info/entry_points.txt
fastapi_file_router/__init__.py
fastapi_file_router/router.py
fastapi_file_router-0.1.17.dist-info/RECORD
