Metadata-Version: 2.1
Name: fastapi-file-router
Version: 0.1.17
Summary: File-based routing for FastAPI
Author-Email: Bewinxed <bewinxed@gmail.com>
License: WhoCares
Project-URL: repository, https://github.com/Bewinxed/fastapi-file-router
Requires-Python: <4.0,>=3.10
